Pardee_Package/__init__.py
Pardee_Package/color_palletes.py
Pardee_Package/example.py
Pardee_Package/style_dictionaries.py
Pardee_Package/test_packages.py
pardeeVisualizationPackage-0.1.2.dist-info/LICENSE.txt
pardeeVisualizationPackage-0.1.2.dist-info/METADATA
pardeeVisualizationPackage-0.1.2.dist-info/WHEEL
pardeeVisualizationPackage-0.1.2.dist-info/top_level.txt
pardeeVisualizationPackage-0.1.2.dist-info/RECORD
