Metadata-Version: 2.1
Name: pardeeVisualizationPackage
Version: 0.1.2
Summary: Package for converting seaborn visualizations into Pardee Center Friendly Packages
Home-page: https://github.com/Coryv221/Pardee_Theme
Author: Cory Vandenberg
Author-email: cory.vandenberg@du.edu
License: UNKNOWN
Platform: UNKNOWN
Classifier: Programming Language :: Python :: 3
Classifier: License :: OSI Approved :: MIT License
Classifier: Operating System :: OS Independent
Requires-Python: >=3.6
